dj_pagination/__init__.py
dj_pagination/middleware.py
dj_pagination/models.py
dj_pagination/paginator.py
dj_pagination/settings.py
dj_pagination/locale/de/LC_MESSAGES/django.po
dj_pagination/locale/es/LC_MESSAGES/django.po
dj_pagination/locale/fi/LC_MESSAGES/django.po
dj_pagination/locale/fr/LC_MESSAGES/django.po
dj_pagination/locale/it/LC_MESSAGES/django.po
dj_pagination/locale/nn/LC_MESSAGES/django.po
dj_pagination/locale/no/LC_MESSAGES/django.po
dj_pagination/locale/pl/LC_MESSAGES/django.po
dj_pagination/locale/pt/LC_MESSAGES/django.po
dj_pagination/locale/pt_BR/LC_MESSAGES/django.po
dj_pagination/locale/ru/LC_MESSAGES/django.po
dj_pagination/locale/tr/LC_MESSAGES/django.po
dj_pagination/templates/pagination/pagination.html
dj_pagination/templatetags/__init__.py
dj_pagination/templatetags/pagination_tags.py
dj_pagination/test_project/__init__.py
dj_pagination/test_project/manage.py
dj_pagination/test_project/settings.py
dj_pagination/test_project/tests.py
dj_pagination/test_project/urls.py
dj_pagination/test_project/example/__init__.py
dj_pagination/test_project/example/models.py
dj_pagination/test_project/example/urls.py
dj_pagination/test_project/example/views.py
dj_pagination/test_project/example/templates/example/list.html
dj_pagination/test_project/example/templates/example/two_lists.html
dj_pagination/test_project/example/templates/pagination/custom_pagination.html
dj_pagination/tests/__init__.py
dj_pagination/tests/runner.py
dj_pagination/tests/settings.py
dj_pagination/tests/test_main.py
dj_pagination-2.4.0.dist-info/METADATA
dj_pagination-2.4.0.dist-info/RECORD
dj_pagination-2.4.0.dist-info/WHEEL
dj_pagination-2.4.0.dist-info/top_level.txt
