Metadata-Version: 2.1
Name: dj-pagination
Version: 2.4.0
Summary: Django + Pagination Made Easy
Home-page: https://github.com/pydanny/dj-pagination
Author: Daniel Roy Greenfeld
Author-email: pydanny@gmail.com
License: BSD
Keywords: pagination,django
Platform: UNKNOWN
Classifier: Development Status :: 4 - Beta
Classifier: Framework :: Django :: 1.11
Classifier: Framework :: Django :: 2.0
Classifier: Framework :: Django :: 2.1
Classifier: Environment :: Web Environment
Classifier: Framework :: Django
Classifier: Intended Audience :: Developers
Classifier: License :: OSI Approved :: BSD License
Classifier: Operating System :: OS Independent
Classifier: Programming Language :: Python :: 2.7
Classifier: Programming Language :: Python :: 3
Classifier: Programming Language :: Python :: 3.4
Classifier: Programming Language :: Python :: 3.5
Classifier: Programming Language :: Python :: 3.6
